openaichatlib/V3.py
openaichatlib/__init__.py
openaichatlib/typings.py
openaichatlib/utils.py
openaichatlib/version.py
openaichatlib-1.1.5.dist-info/LICENSE
openaichatlib-1.1.5.dist-info/METADATA
openaichatlib-1.1.5.dist-info/WHEEL
openaichatlib-1.1.5.dist-info/top_level.txt
openaichatlib-1.1.5.dist-info/RECORD
