Metadata-Version: 2.1
Name: openaichatlib
Version: 1.1.5
Summary: OpenAI Chat API
Home-page: https://github.com/IAn2018cs/OpenAIChatLib
Author: IAn2018
Author-email: ian2018cs@gmail.com
Keywords: openai,ChatGPT,api,chat
Classifier: License :: OSI Approved :: MIT License
Classifier: Programming Language :: Python
Classifier: Programming Language :: Python :: 3 :: Only
Classifier: Programming Language :: Python :: 3.9
Classifier: Programming Language :: Python :: 3.10
Classifier: Programming Language :: Python :: 3.11
Classifier: Programming Language :: Python :: 3.12
Requires-Python: >=3.9, <3.13
License-File: LICENSE
Requires-Dist: requests[socks]
